LICENSE
MANIFEST.in
README.md
setup.py
promptly/__init__.py
promptly/compat.py
promptly/exceptions.py
promptly/form.py
promptly/inputs.py
promptly/styles.py
promptly/utils.py
promptly.egg-info/PKG-INFO
promptly.egg-info/SOURCES.txt
promptly.egg-info/dependency_links.txt
promptly.egg-info/requires.txt
promptly.egg-info/top_level.txt
promptly/renderers/__init__.py
promptly/renderers/console.py
promptly/renderers/core.py
promptly/resources/__init__.py
promptly/resources/default.css
promptly/runners/__init__.py
promptly/runners/console.py