Metadata-Version: 1.1
Name: promptly
Version: 0.6.3
Summary: Console Prompting
Home-page: https://github.com/aventurella/promptly
Author: Aubrey Taylor <aubricus@gmail.com>, Adam Venturella <aventurella@gmail.com>
Author-email: aubricus@gmail.com, aventurella@gmail.com
License: Copyright (c) 2013 Aubrey Taylor and Adam Venturella.
